github_push_gui/__init__.py
github_push_gui/main.py
github_push_gui-1.1.3.dist-info/METADATA
github_push_gui-1.1.3.dist-info/WHEEL
github_push_gui-1.1.3.dist-info/top_level.txt
github_push_gui-1.1.3.dist-info/RECORD
